orm_converter/__init__.py
orm_converter/bases.py
orm_converter/shared/__init__.py
orm_converter/shared/exceptions.py
orm_converter/shared/utils.py
orm_converter/tortoise_to_django/__init__.py
orm_converter/tortoise_to_django/field_converter.py
orm_converter/tortoise_to_django/model_converter.py
orm_converter-0.2.2b0.dist-info/LICENSE
orm_converter-0.2.2b0.dist-info/METADATA
orm_converter-0.2.2b0.dist-info/WHEEL
orm_converter-0.2.2b0.dist-info/top_level.txt
orm_converter-0.2.2b0.dist-info/RECORD
