Metadata-Version: 2.1
Name: orm-converter
Version: 0.2.2b0
Summary: A utility that allows you to convert ORM models.
Home-page: https://github.com/MaximZayats/orm-converter
Author: Maxim
Author-email: maximzayats1@gmail.com
License: MIT
Keywords: python,django,orm,conversion,orm-framework,tortoise-orm,django-orm,admin-panel
Platform: UNKNOWN
License-File: LICENSE
Requires-Dist: tortoise-orm (~=0.17.6)
Requires-Dist: Django (~=3.2.6)
